{
	"LineEntries": [
		{
			"BackgroundColor": 2,
			"ForegroundColor": 15,
			"Text": "Your available choices are:"
		},
		{
			"BackgroundColor": 15,
			"ForegroundColor": 12,
			"Text": "0. Exit"
		},
		{
			"BackgroundColor": 15,
			"ForegroundColor": 0,
			"Text": "1. List all Polar bears"
		},
		{
			"BackgroundColor": 15,
			"ForegroundColor": 0,
			"Text": "2. Create a new polar bear"
		},
		{
			"BackgroundColor": 15,
			"ForegroundColor": 0,
			"Text": "3. Delete existing polar bear"
		},
		{
			"BackgroundColor": 15,
			"ForegroundColor": 0,
			"Text": "4. Modify existing polar bear"
		},
		{
			"BackgroundColor": 0,
			"ForegroundColor": 15,
			"Text": "Please enter your choice: "
		}
	]
}